gitvoyager/__init__.py
gitvoyager/main.py
gitvoyager-2.2.0.dist-info/METADATA
gitvoyager-2.2.0.dist-info/WHEEL
gitvoyager-2.2.0.dist-info/entry_points.txt
gitvoyager-2.2.0.dist-info/top_level.txt
gitvoyager-2.2.0.dist-info/RECORD
