Metadata-Version: 2.1
Name: gitvoyager
Version: 2.2.0
Requires-Dist: requests
